{
  "0": {
    "abdominal_pain": 0,
    "anaemia": 0,
    "abortions": 0,
    "acetone": 0,
    "aggression": 0,
    "arthrogyposis": 0,
    "ankylosis": 0,
    "anxiety": 0,
    "bellowing": 0,
    "blood_loss": 0,
    "blood_poisoning": 0,
    "blisters": 0,
    "colic": 0,
    "Condemnation_of_livers": 0,
    "conjunctivae": 0,
    "coughing": 0,
    "depression": 0,
    "discomfort": 0,
    "dyspnea": 0,
    "dysentery": 0,
    "diarrhoea": 0,
    "dehydration": 0,
    "drooling": 0,
    "dull": 0,
    "decreased_fertility": 0,
    "diffculty_breath": 0,
    "emaciation": 0,
    "encephalitis": 0,
    "fever": 0,
    "facial_paralysis": 0,
    "frothing_of_mouth": 0,
    "frothing": 0,
    "gaseous_stomach": 0,
    "highly_diarrhoea": 0,
    "high_pulse_rate": 0,
    "high_temp": 1,
    "high_proportion": 0,
    "hyperaemia": 0,
    "hydrocephalus": 0,
    "isolation_from_herd": 0,
    "infertility": 0,
    "intermittent_fever": 0,
    "jaundice": 0,
    "ketosis": 0,
    "loss_of_appetite": 0,
    "lameness": 0,
    "lack_of-coordination": 0,
    "lethargy": 0,
    "lacrimation": 0,
    "milk_flakes": 0,
    "milk_watery": 0,
    "milk_clots": 0,
    "mild_diarrhoea": 0,
    "moaning": 1,
    "mucosal_lesions": 0,
    "milk_fever": 0,
    "nausea": 0,
    "nasel_discharges": 0,
    "oedema": 0,
    "pain": 0,
    "painful_tongue": 0,
    "pneumonia": 0,
    "photo_sensitization": 0,
    "quivering_lips": 0,
    "reduction_milk_vields": 1,
    "rapid_breathing": 0,
    "rumenstasis": 0,
    "reduced_rumination": 0,
    "reduced_fertility": 0,
    "reduced_fat": 0,
    "reduces_feed_intake": 1,
    "raised_breathing": 0,
    "stomach_pain": 0,
    "salivation": 0,
    "stillbirths": 0,
    "shallow_breathing": 1,
    "swollen_pharyngeal": 0,
    "swelling": 0,
    "saliva": 0,
    "swollen_tongue": 0,
    "tachycardia": 0,
    "torticollis": 0,
    "udder_swelling": 0,
    "udder_heat": 0,
    "udder_hardeness": 0,
    "udder_redness": 0,
    "udder_pain": 0,
    "unwillingness_to_move": 0,
    "ulcers": 0,
    "vomiting": 0,
    "weight_loss": 0,
    "weakness": 0,
    "prognosis": "traumatic_reticulitis"
  },
  "1": {
    "abdominal_pain": 0,
    "anaemia": 0,
    "abortions": 1,
    "acetone": 0,
    "aggression": 0,
    "arthrogyposis": 0,
    "ankylosis": 0,
    "anxiety": 0,
    "bellowing": 0,
    "blood_loss": 0,
    "blood_poisoning": 0,
    "blisters": 0,
    "colic": 0,
    "Condemnation_of_livers": 0,
    "conjunctivae": 1,
    "coughing": 0,
    "depression": 0,
    "discomfort": 0,
    "dyspnea": 0,
    "dysentery": 0,
    "diarrhoea": 0,
    "dehydration": 0,
    "drooling": 0,
    "dull": 0,
    "decreased_fertility": 0,
    "diffculty_breath": 0,
    "emaciation": 0,
    "encephalitis": 0,
    "fever": 1,
    "facial_paralysis": 0,
    "frothing_of_mouth": 0,
    "frothing": 0,
    "gaseous_stomach": 0,
    "highly_diarrhoea": 0,
    "high_pulse_rate": 0,
    "high_temp": 0,
    "high_proportion": 0,
    "hyperaemia": 0,
    "hydrocephalus": 0,
    "isolation_from_herd": 0,
    "infertility": 0,
    "intermittent_fever": 0,
    "jaundice": 0,
    "ketosis": 0,
    "loss_of_appetite": 0,
    "lameness": 0,
    "lack_of-coordination": 0,
    "lethargy": 0,
    "lacrimation": 0,
    "milk_flakes": 0,
    "milk_watery": 0,
    "milk_clots": 0,
    "mild_diarrhoea": 0,
    "moaning": 0,
    "mucosal_lesions": 0,
    "milk_fever": 0,
    "nausea": 0,
    "nasel_discharges": 0,
    "oedema": 0,
    "pain": 0,
    "painful_tongue": 0,
    "pneumonia": 0,
    "photo_sensitization": 0,
    "quivering_lips": 0,
    "reduction_milk_vields": 0,
    "rapid_breathing": 0,
    "rumenstasis": 0,
    "reduced_rumination": 0,
    "reduced_fertility": 0,
    "reduced_fat": 0,
    "reduces_feed_intake": 0,
    "raised_breathing": 0,
    "stomach_pain": 0,
    "salivation": 0,
    "stillbirths": 0,
    "shallow_breathing": 0,
    "swollen_pharyngeal": 0,
    "swelling": 0,
    "saliva": 0,
    "swollen_tongue": 0,
    "tachycardia": 0,
    "torticollis": 0,
    "udder_swelling": 0,
    "udder_heat": 0,
    "udder_hardeness": 0,
    "udder_redness": 0,
    "udder_pain": 0,
    "unwillingness_to_move": 0,
    "ulcers": 0,
    "vomiting": 0,
    "weight_loss": 0,
    "weakness": 1,
    "prognosis": "rift_valley_fever"
  }
}